Metadata-Version: 2.4
Name: py-synologydsm-api
Version: 2.7.3
Summary: Python API for communication with Synology DSM
Home-page: https://github.com/mib1185/py-synologydsm-api#readme
Author: Michael Brussk (mib1185), Quentin POLLET (Quentame), FG van Zeelst (ProtoThis)
License: MIT
Project-URL: Changelog, https://github.com/mib1185/py-synologydsm-api/releases
Project-URL: Repository, https://github.com/mib1185/py-synologydsm-api
Project-URL: Documentation, https://github.com/mib1185/py-synologydsm-api#readme
Keywords: synology-dsm,synology
Classifier: Development Status :: 5 - Production/Stable
Classifier: Intended Audience :: Developers
Classifier: License :: OSI Approved :: MIT License
Classifier: Operating System :: OS Independent
Classifier: Programming Language :: Python :: 3.9
Classifier: Programming Language :: Python :: 3.10
Classifier: Programming Language :: Python :: 3.11
Classifier: Programming Language :: Python :: 3.12
Classifier: Programming Language :: Python :: 3.13
Classifier: Topic :: Software Development :: Libraries
Requires-Python: >=3.9
License-File: LICENSE.txt
Requires-Dist: aiohttp
Requires-Dist: aiofiles
Requires-Dist: awesomeversion
Dynamic: license-file
